setup.cfg
setup.py
lru/__init__.py
py_lru_cache.egg-info/PKG-INFO
py_lru_cache.egg-info/SOURCES.txt
py_lru_cache.egg-info/dependency_links.txt
py_lru_cache.egg-info/top_level.txt