Metadata-Version: 1.0
Name: py-lru-cache
Version: 0.1.1
Summary: LRU cache for python. Provides a dictionary-like object as well as a method decorator.
Home-page: https://github.com/stucchio/Python-LRU-cache
Author: Chris Stucchio
Author-email: stucchio@gmail.com
License: Dual: GPL v3 or BSD
Platform: UNKNOWN
